nonebot_plugin_suggarchat/API.py
nonebot_plugin_suggarchat/__init__.py
nonebot_plugin_suggarchat/builtin_hook.py
nonebot_plugin_suggarchat/chatmanager.py
nonebot_plugin_suggarchat/check_rule.py
nonebot_plugin_suggarchat/config.py
nonebot_plugin_suggarchat/event.py
nonebot_plugin_suggarchat/exception.py
nonebot_plugin_suggarchat/hook_manager.py
nonebot_plugin_suggarchat/matcher.py
nonebot_plugin_suggarchat/matcher_manager.py
nonebot_plugin_suggarchat/on_event.py
nonebot_plugin_suggarchat/preprocess.py
nonebot_plugin_suggarchat/send.py
nonebot_plugin_suggarchat/handlers/add_notices.py
nonebot_plugin_suggarchat/handlers/chat.py
nonebot_plugin_suggarchat/handlers/chatobj.py
nonebot_plugin_suggarchat/handlers/choose_prompt.py
nonebot_plugin_suggarchat/handlers/debug_switchs.py
nonebot_plugin_suggarchat/handlers/del_memory.py
nonebot_plugin_suggarchat/handlers/disable.py
nonebot_plugin_suggarchat/handlers/enable.py
nonebot_plugin_suggarchat/handlers/fakepeople_switch.py
nonebot_plugin_suggarchat/handlers/insights.py
nonebot_plugin_suggarchat/handlers/mcp.py
nonebot_plugin_suggarchat/handlers/menus.py
nonebot_plugin_suggarchat/handlers/poke_event.py
nonebot_plugin_suggarchat/handlers/preset_test.py
nonebot_plugin_suggarchat/handlers/presets.py
nonebot_plugin_suggarchat/handlers/prompt.py
nonebot_plugin_suggarchat/handlers/recall.py
nonebot_plugin_suggarchat/handlers/sessions.py
nonebot_plugin_suggarchat/handlers/set_preset.py
nonebot_plugin_suggarchat/handlers/show_abstract.py
nonebot_plugin_suggarchat/migrations/1d99948099bb_fix_memory.py
nonebot_plugin_suggarchat/migrations/25b14ed0ad3c_insights.py
nonebot_plugin_suggarchat/migrations/3537b7cb6a29_init.py
nonebot_plugin_suggarchat/migrations/40596fc17a61_upd_amrita.py
nonebot_plugin_suggarchat/migrations/5740c5aae763_json.py
nonebot_plugin_suggarchat/migrations/ec1f1e46989b_usage.py
nonebot_plugin_suggarchat/utils/admin.py
nonebot_plugin_suggarchat/utils/event.py
nonebot_plugin_suggarchat/utils/functions.py
nonebot_plugin_suggarchat-3.7.0.dist-info/licenses/LICENSE
nonebot_plugin_suggarchat-3.7.0.dist-info/METADATA
nonebot_plugin_suggarchat-3.7.0.dist-info/WHEEL
nonebot_plugin_suggarchat-3.7.0.dist-info/top_level.txt
nonebot_plugin_suggarchat-3.7.0.dist-info/RECORD
