Metadata-Version: 2.4
Name: nonebot_plugin_suggarchat
Version: 3.7.0
Summary: SuggarChat chat framework
Author-email: LiteSuggarDEV <windowserror@163.com>
License: GPL-3.0-or-later
Project-URL: Homepage, https://github.com/LiteSuggarDEV/nonebot_plugin_suggarchat
Project-URL: Source, https://github.com/LiteSuggarDEV/nonebot_plugin_suggarchat
Project-URL: Issue Tracker, https://github.com/LiteSuggarDEV/nonebot_plugin_suggarchat/issues
Keywords: chat", "suggar", "nonebot
Requires-Python: <3.14,>=3.10
License-File: LICENSE
Requires-Dist: jieba>=0.42.1
Requires-Dist: nonebot2[fastapi]>=2.2.0
Requires-Dist: openai<=1.99.0,>=1.66.3
Requires-Dist: pydantic>=2.4.2
Requires-Dist: nonebot-adapter-onebot>=2.0.0
Requires-Dist: nonebot-plugin-localstore>=0.7
Requires-Dist: typing-extensions>=4.6.0
Requires-Dist: pytz>=2025.1
Requires-Dist: tomli>=2.0.0
Requires-Dist: tomli-w>=1.0.0
Requires-Dist: stubs>=1.0.0
Requires-Dist: dotenv>=0.9.9
Requires-Dist: aiofiles>=24.1.0
Requires-Dist: importlib>=1.0.4
Requires-Dist: watchfiles>=0.18.0
Requires-Dist: nonebot-plugin-orm>=0.8.3
Requires-Dist: fastmcp>=2.13.1
Requires-Dist: zipp>=3.23.0
Requires-Dist: nonebot-plugin-uniconf>=0.1.1
Provides-Extra: openai
Provides-Extra: cloudflare
Requires-Dist: nonebot_plugin_suggarex_cf>=2.0.0; extra == "cloudflare"
Provides-Extra: full
Requires-Dist: nonebot_plugin_suggarex_cf>=2.0.0; extra == "full"
Provides-Extra: amrita
Requires-Dist: amrita>=0.2.0.post2; extra == "amrita"
Dynamic: license-file
